torstomp
