Metadata-Version: 1.0
Name: torstomp
Version: 0.1.7
Summary: Simple Stomp 1.1 client for tornado applications
Home-page: https://github.com/wpjunior/torstomp.git
Author: Wilson Júnior
Author-email: wilsonpjunior@gmail.com
License: MIT
Keywords: stomp
Platform: any
